aiogram_events/__init__.py
aiogram_events/decorators/__init__.py
aiogram_events/decorators/decorators.py
aiogram_events/event/__init__.py
aiogram_events/event/event.py
aiogram_events/event/event_group.py
aiogram_events/stepper/__init__.py
aiogram_events/stepper/entry.py
aiogram_events/stepper/stepper.py
aiogram_events/utils/__init__.py
aiogram_events/utils/utils.py
aiogram_events-0.2.1.dist-info/LICENSE.md
aiogram_events-0.2.1.dist-info/METADATA
aiogram_events-0.2.1.dist-info/WHEEL
aiogram_events-0.2.1.dist-info/top_level.txt
aiogram_events-0.2.1.dist-info/RECORD
