Metadata-Version: 2.1
Name: aiogram_events
Version: 0.2.1
Summary: A simple way to catch and process events in the aiogram library.
Author-email: iwatkot <iwatkot@gmail.com>
License: MIT License
Project-URL: Homepage, https://github.com/iwatkot/aiogram_events
Project-URL: Repository, https://github.com/iwatkot/aiogram_events
Keywords: telegram,aiogram,events,handlers
Classifier: Programming Language :: Python :: 3.10
Classifier: Programming Language :: Python :: 3.11
Classifier: Programming Language :: Python :: 3.12
Classifier: License :: OSI Approved :: MIT License
Classifier: Operating System :: OS Independent
License-File: LICENSE.md
Requires-Dist: aiogram >=3.0.0
